{
  "userId": 12,
  "productsInCart": [{
    "id": 4,
    "imageUrl": "1244",
    "productName": "HP Spectre x360 - 13-4101dx",
    "color" :"FFF",
    "quantity": 1,
    "price": 0
  },{
    "id": 101,
    "imageUrl": "1241",
    "productName": "Beats Studio 2 Over-Ear Red Headphones",
    "color" :"F00",
    "quantity": 5,
    "price": 14.99
  }],

  "you_may_also_be_interested": [{
    "id": 3000,
    "productName": "EliteBook 850",
    "price": 1039,
    "imageUrl": "css/images/Popular-item3.jpg"
  }, {
    "id": 3001,
    "productName": "HP EliteBook Folio",
    "price": 550,
    "imageUrl": "css/images/Popular-item3.jpg"
  }, {
    "id": 3002,
    "productName": "HP EliteBook Folio",
    "price": 550,
    "imageUrl": "css/images/Popular-item3.jpg"
  }, {
    "id": 3003,
    "productName": "HP EliteBook Folio",
    "price": 550,
    "imageUrl": "css/images/Popular-item3.jpg"
  }]

}